datasae/__init__.py
datasae/__main__.py
datasae/boolean.py
datasae/exception.py
datasae/float.py
datasae/integer.py
datasae/string.py
datasae/timestamp.py
datasae/utils.py
datasae/converter/__init__.py
datasae/converter/gsheet.py
datasae/converter/local.py
datasae/converter/s3.py
datasae/converter/sql.py
DataSae-0.5.3.dist-info/LICENSE
DataSae-0.5.3.dist-info/METADATA
DataSae-0.5.3.dist-info/WHEEL
DataSae-0.5.3.dist-info/entry_points.txt
DataSae-0.5.3.dist-info/top_level.txt
DataSae-0.5.3.dist-info/RECORD
