Metadata-Version: 2.1
Name: DataSae
Version: 0.5.3
Summary: Data Quality Framework provides by Jabar Digital Service
Home-page: https://github.com/jabardigitalservice/DataSae
Author: pipinfitriadi@gmail.com, agistyaanugrah@gmail.com, riskaamalia.mail@gmail.com, rizky.prilian@gmail.com, misdan.wijaya07@gmail.com, fauzanmrabbani@gmail.com, hanieffatchudin@gmail.com, adibintangprada@gmail.com, firmanramadan97@gmail.com, raihanjauhari@gmail.com, pujinhidayah@gmail.com
Maintainer: dataengineering@digitalservice.id, jds.dataengineer@gmail.com
License: AGPL-3.0-only
Project-URL: Docs, https://jabardigitalservice.github.io/DataSae/
Project-URL: Repository, https://github.com/jabardigitalservice/DataSae
Keywords: data quality framework,data sae,good data,data bagus,validation,jds,jabar digital service,data engineer
Classifier: Development Status :: 2 - Pre-Alpha
Classifier: Programming Language :: Python :: 3.8
Classifier: License :: OSI Approved :: GNU Affero General Public License v3
Classifier: Operating System :: OS Independent
Classifier: Topic :: Software Development :: Quality Assurance
Requires-Python: >=3.8
License-File: LICENSE
Requires-Dist: pandas
Requires-Dist: typer[all]
Provides-Extra: converter
Requires-Dist: pyyaml ; extra == 'converter'
Requires-Dist: fastparquet ; extra == 'converter'
Requires-Dist: openpyxl ; extra == 'converter'
Provides-Extra: gsheet
Requires-Dist: google-api-python-client ; extra == 'gsheet'
Requires-Dist: gspread ==5.12.0 ; extra == 'gsheet'
Provides-Extra: s3
Requires-Dist: minio ; extra == 's3'
Provides-Extra: sql
Requires-Dist: sqlalchemy ; extra == 'sql'
Requires-Dist: psycopg2-binary ; extra == 'sql'
Requires-Dist: mysqlclient ; extra == 'sql'
Requires-Dist: pymysql ; extra == 'sql'
